convars/__init__.py
convars/cli.py
convars-0.2.0.dist-info/METADATA
convars-0.2.0.dist-info/WHEEL
convars-0.2.0.dist-info/entry_points.txt
convars-0.2.0.dist-info/top_level.txt
convars-0.2.0.dist-info/RECORD
