Metadata-Version: 2.1
Name: convars
Version: 0.2.0
Author-email: Dan Kelleher <kelleherjdan@gmail.com>
License: MIT
Classifier: License :: OSI Approved :: MIT License
Classifier: Programming Language :: Python
Classifier: Programming Language :: Python :: 3
Requires-Dist: python-dotenv
Requires-Dist: click
Provides-Extra: dev
Requires-Dist: black ; extra == 'dev'
